roc_face/__init__.py
roc_face/base.py
roc_face/exceptions.py
roc_face/fit_functions.py
roc_face/measures.py
roc_face/models.py
roc_face/utils.py
roc_face-0.1.1.dist-info/METADATA
roc_face-0.1.1.dist-info/WHEEL
roc_face-0.1.1.dist-info/top_level.txt
roc_face-0.1.1.dist-info/RECORD
