Metadata-Version: 2.1
Name: roc-face
Version: 0.1.1
Summary: A package to fit models to recognition memory ROC data and compute signal detection measures.
Author: Lewis Dunne
Project-URL: repository, https://github.com/lcdunne/roc-face
Keywords: signal detection theory,receiver operating characteristics,ROC,psychology
Classifier: Programming Language :: Python :: 3
Classifier: License :: OSI Approved :: GNU General Public License v3 (GPLv3)
Classifier: Operating System :: OS Independent
Requires-Python: >=3.7
Requires-Dist: numpy
Requires-Dist: scipy
Requires-Dist: prettytable
